fetchdep/__init__.py
fetchdep/__main__.py
fetchdep/config.py
fetchdep/database.py
fetchdep/defs.py
fetchdep/dependency.py
fetchdep/engine.py
fetchdep/exceptions.py
fetchdep/opts.py
fetchdep/processor.py
fetchdep/fetch/__init__.py
fetchdep/fetch/cvs.py
fetchdep/fetch/git.py
fetchdep/fetch/mercurial.py
fetchdep/fetch/mkdir.py
fetchdep/fetch/svn.py
fetchdep/tool/__init__.py
fetchdep/tool/cvs.py
fetchdep/tool/git.py
fetchdep/tool/hg.py
fetchdep/tool/svn.py
fetchdep/util/__init__.py
fetchdep/util/compat.py
fetchdep/util/enum.py
fetchdep/util/io.py
fetchdep/util/log.py
fetchdep/util/string.py
fetchdep/util/tags.py
fetchdep/util/win32.py
fetchdep-0.0.0.dist-info/LICENSE
fetchdep-0.0.0.dist-info/METADATA
fetchdep-0.0.0.dist-info/WHEEL
fetchdep-0.0.0.dist-info/entry_points.txt
fetchdep-0.0.0.dist-info/top_level.txt
fetchdep-0.0.0.dist-info/RECORD
